pypiratzzi/__init__.py
pypiratzzi/cli.py
pypiratzzi-23.8.0.dist-info/METADATA
pypiratzzi-23.8.0.dist-info/WHEEL
pypiratzzi-23.8.0.dist-info/entry_points.txt
pypiratzzi-23.8.0.dist-info/licenses/LICENSE
pypiratzzi-23.8.0.dist-info/RECORD
