Metadata-Version: 2.1
Name: pypiratzzi
Version: 23.8.0
Summary: pypiratzzi downloads signatures from PyPI.
Author-email: meejah <meejah@meejah.ca>
License: GPL
License-File: LICENSE
Keywords: cryptography,pypi,signatures
Classifier: Framework :: Twisted
Classifier: Programming Language :: Python :: 3
Requires-Python: >=3.6
Requires-Dist: click
Requires-Dist: setuptools
Requires-Dist: treq
Requires-Dist: twisted
Provides-Extra: dev
Requires-Dist: dulwich; extra == 'dev'
Requires-Dist: gpg; extra == 'dev'
Requires-Dist: hatchling; extra == 'dev'
Requires-Dist: pip-tools; extra == 'dev'
Requires-Dist: readme-renderer; extra == 'dev'
Requires-Dist: sphinx; extra == 'dev'
Requires-Dist: twine; extra == 'dev'
Provides-Extra: test
Requires-Dist: cuvner; extra == 'test'
Requires-Dist: pytest; extra == 'test'
Requires-Dist: pytest-cov; extra == 'test'
Requires-Dist: pytest-twisted; extra == 'test'
